{
    "swagger": "2.0",
    "info": {
        "description": "REST API for restaurant hall, orders, and warehouse management",
        "title": "Restaurant Management System API",
        "contact": {},
        "version": "1.0"
    },
    "basePath": "/api",
    "paths": {
        "/api/batch-import/products": {
            "post": {
                "consumes": [
                    "application/json"
                ],
                "produces": [
                    "application/json"
                ],
                "tags": [
                    "batch-import"
                ],
                "summary": "Batch import products from JSON array or CSV (name,unit,cost_price,is_available)",
                "responses": {
                    "200": {
                        "description": "OK",
                        "schema": {
                            "type": "object",
                            "additionalProperties": {
                                "type": "integer"
                            }
                        }
                    }
                }
            }
        },
        "/api/customers": {
            "get": {
                "produces": [
                    "application/json"
                ],
                "tags": [
                    "customers"
                ],
                "summary": "List customers",
                "responses": {
                    "200": {
                        "description": "OK",
                        "schema": {
                            "type": "array",
                            "items": {
                                "$ref": "#/definitions/domain.Customer"
                            }
                        }
                    }
                }
            },
            "post": {
                "consumes": [
                    "application/json"
                ],
                "produces": [
                    "application/json"
                ],
                "tags": [
                    "customers"
                ],
                "summary": "Create customer",
                "parameters": [
                    {
                        "description": "customer",
                        "name": "customer",
                        "in": "body",
                        "required": true,
                        "schema": {
                            "$ref": "#/definitions/domain.Customer"
                        }
                    }
                ],
                "responses": {
                    "201": {
                        "description": "Created",
                        "schema": {
                            "$ref": "#/definitions/domain.Customer"
                        }
                    }
                }
            }
        },
        "/api/customers/{id}": {
            "put": {
                "consumes": [
                    "application/json"
                ],
                "produces": [
                    "application/json"
                ],
                "tags": [
                    "customers"
                ],
                "summary": "Update customer",
                "parameters": [
                    {
                        "type": "integer",
                        "description": "customer id",
                        "name": "id",
                        "in": "path",
                        "required": true
                    },
                    {
                        "description": "customer",
                        "name": "customer",
                        "in": "body",
                        "required": true,
                        "schema": {
                            "$ref": "#/definitions/domain.Customer"
                        }
                    }
                ],
                "responses": {
                    "200": {
                        "description": "OK",
                        "schema": {
                            "$ref": "#/definitions/domain.Customer"
                        }
                    }
                }
            },
            "delete": {
                "tags": [
                    "customers"
                ],
                "summary": "Delete customer",
                "parameters": [
                    {
                        "type": "integer",
                        "description": "customer id",
                        "name": "id",
                        "in": "path",
                        "required": true
                    }
                ],
                "responses": {
                    "204": {
                        "description": "No Content"
                    }
                }
            }
        },
        "/api/dishes": {
            "get": {
                "produces": [
                    "application/json"
                ],
                "tags": [
                    "dishes"
                ],
                "summary": "List dishes",
                "parameters": [
                    {
                        "type": "integer",
                        "description": "limit",
                        "name": "limit",
                        "in": "query"
                    }
                ],
                "responses": {
                    "200": {
                        "description": "OK",
                        "schema": {
                            "type": "array",
                            "items": {
                                "$ref": "#/definitions/domain.Dish"
                            }
                        }
                    }
                }
            },
            "post": {
                "consumes": [
                    "application/json"
                ],
                "produces": [
                    "application/json"
                ],
                "tags": [
                    "dishes"
                ],
                "summary": "Create or update dish",
                "parameters": [
                    {
                        "description": "dish",
                        "name": "dish",
                        "in": "body",
                        "required": true,
                        "schema": {
                            "$ref": "#/definitions/domain.Dish"
                        }
                    }
                ],
                "responses": {
                    "200": {
                        "description": "OK",
                        "schema": {
                            "$ref": "#/definitions/domain.Dish"
                        }
                    }
                }
            }
        },
        "/api/dishes/{id}": {
            "delete": {
                "tags": [
                    "dishes"
                ],
                "summary": "Delete dish",
                "parameters": [
                    {
                        "type": "integer",
                        "description": "dish id",
                        "name": "id",
                        "in": "path",
                        "required": true
                    }
                ],
                "responses": {
                    "204": {
                        "description": "No Content"
                    }
                }
            }
        },
        "/api/employees": {
            "get": {
                "produces": [
                    "application/json"
                ],
                "tags": [
                    "employees"
                ],
                "summary": "List employees",
                "responses": {
                    "200": {
                        "description": "OK",
                        "schema": {
                            "type": "array",
                            "items": {
                                "$ref": "#/definitions/domain.Employee"
                            }
                        }
                    }
                }
            },
            "post": {
                "consumes": [
                    "application/json"
                ],
                "produces": [
                    "application/json"
                ],
                "tags": [
                    "employees"
                ],
                "summary": "Create employee",
                "parameters": [
                    {
                        "description": "employee",
                        "name": "employee",
                        "in": "body",
                        "required": true,
                        "schema": {
                            "$ref": "#/definitions/domain.Employee"
                        }
                    }
                ],
                "responses": {
                    "201": {
                        "description": "Created",
                        "schema": {
                            "$ref": "#/definitions/domain.Employee"
                        }
                    }
                }
            }
        },
        "/api/employees/{id}": {
            "put": {
                "consumes": [
                    "application/json"
                ],
                "produces": [
                    "application/json"
                ],
                "tags": [
                    "employees"
                ],
                "summary": "Update employee",
                "parameters": [
                    {
                        "type": "integer",
                        "description": "employee id",
                        "name": "id",
                        "in": "path",
                        "required": true
                    },
                    {
                        "description": "employee",
                        "name": "employee",
                        "in": "body",
                        "required": true,
                        "schema": {
                            "$ref": "#/definitions/domain.Employee"
                        }
                    }
                ],
                "responses": {
                    "200": {
                        "description": "OK",
                        "schema": {
                            "$ref": "#/definitions/domain.Employee"
                        }
                    }
                }
            },
            "delete": {
                "tags": [
                    "employees"
                ],
                "summary": "Delete employee",
                "parameters": [
                    {
                        "type": "integer",
                        "description": "employee id",
                        "name": "id",
                        "in": "path",
                        "required": true
                    }
                ],
                "responses": {
                    "204": {
                        "description": "No Content"
                    }
                }
            }
        },
        "/api/menu-categories": {
            "get": {
                "produces": [
                    "application/json"
                ],
                "tags": [
                    "menu-categories"
                ],
                "summary": "List menu categories",
                "responses": {
                    "200": {
                        "description": "OK",
                        "schema": {
                            "type": "array",
                            "items": {
                                "$ref": "#/definitions/domain.MenuCategory"
                            }
                        }
                    }
                }
            },
            "post": {
                "consumes": [
                    "application/json"
                ],
                "produces": [
                    "application/json"
                ],
                "tags": [
                    "menu-categories"
                ],
                "summary": "Create or update menu category",
                "parameters": [
                    {
                        "description": "category",
                        "name": "category",
                        "in": "body",
                        "required": true,
                        "schema": {
                            "$ref": "#/definitions/domain.MenuCategory"
                        }
                    }
                ],
                "responses": {
                    "200": {
                        "description": "OK",
                        "schema": {
                            "$ref": "#/definitions/domain.MenuCategory"
                        }
                    }
                }
            }
        },
        "/api/menu-categories/{id}": {
            "delete": {
                "tags": [
                    "menu-categories"
                ],
                "summary": "Delete menu category",
                "parameters": [
                    {
                        "type": "integer",
                        "description": "category id",
                        "name": "id",
                        "in": "path",
                        "required": true
                    }
                ],
                "responses": {
                    "204": {
                        "description": "No Content"
                    }
                }
            }
        },
        "/api/orders": {
            "get": {
                "produces": [
                    "application/json"
                ],
                "tags": [
                    "orders"
                ],
                "summary": "List orders",
                "parameters": [
                    {
                        "type": "string",
                        "description": "status filter",
                        "name": "status",
                        "in": "query"
                    },
                    {
                        "type": "integer",
                        "description": "limit",
                        "name": "limit",
                        "in": "query"
                    }
                ],
                "responses": {
                    "200": {
                        "description": "OK",
                        "schema": {
                            "type": "array",
                            "items": {
                                "$ref": "#/definitions/domain.Order"
                            }
                        }
                    }
                }
            },
            "post": {
                "consumes": [
                    "application/json"
                ],
                "produces": [
                    "application/json"
                ],
                "tags": [
                    "orders"
                ],
                "summary": "Create order with items",
                "parameters": [
                    {
                        "description": "order",
                        "name": "order",
                        "in": "body",
                        "required": true,
                        "schema": {
                            "$ref": "#/definitions/handlers.orderRequest"
                        }
                    }
                ],
                "responses": {
                    "201": {
                        "description": "Created",
                        "schema": {
                            "$ref": "#/definitions/domain.Order"
                        }
                    }
                }
            }
        },
        "/api/orders/{id}/items": {
            "get": {
                "produces": [
                    "application/json"
                ],
                "tags": [
                    "orders"
                ],
                "summary": "List items for order",
                "parameters": [
                    {
                        "type": "integer",
                        "description": "order id",
                        "name": "id",
                        "in": "path",
                        "required": true
                    }
                ],
                "responses": {
                    "200": {
                        "description": "OK",
                        "schema": {
                            "type": "array",
                            "items": {
                                "$ref": "#/definitions/domain.OrderItem"
                            }
                        }
                    }
                }
            },
            "post": {
                "consumes": [
                    "application/json"
                ],
                "produces": [
                    "application/json"
                ],
                "tags": [
                    "orders"
                ],
                "summary": "Add or update order item",
                "parameters": [
                    {
                        "type": "integer",
                        "description": "order id",
                        "name": "id",
                        "in": "path",
                        "required": true
                    },
                    {
                        "description": "item",
                        "name": "item",
                        "in": "body",
                        "required": true,
                        "schema": {
                            "$ref": "#/definitions/domain.OrderItem"
                        }
                    }
                ],
                "responses": {
                    "200": {
                        "description": "OK"
                    }
                }
            }
        },
        "/api/orders/{id}/items/{itemId}": {
            "delete": {
                "tags": [
                    "orders"
                ],
                "summary": "Delete order item",
                "parameters": [
                    {
                        "type": "integer",
                        "description": "order id",
                        "name": "id",
                        "in": "path",
                        "required": true
                    },
                    {
                        "type": "integer",
                        "description": "item id",
                        "name": "itemId",
                        "in": "path",
                        "required": true
                    }
                ],
                "responses": {
                    "204": {
                        "description": "No Content"
                    }
                }
            }
        },
        "/api/orders/{id}/status": {
            "put": {
                "tags": [
                    "orders"
                ],
                "summary": "Update order status",
                "parameters": [
                    {
                        "type": "integer",
                        "description": "order id",
                        "name": "id",
                        "in": "path",
                        "required": true
                    },
                    {
                        "type": "string",
                        "description": "new status",
                        "name": "status",
                        "in": "query",
                        "required": true
                    }
                ],
                "responses": {
                    "200": {
                        "description": "OK"
                    }
                }
            }
        },
        "/api/payments": {
            "post": {
                "consumes": [
                    "application/json"
                ],
                "produces": [
                    "application/json"
                ],
                "tags": [
                    "payments"
                ],
                "summary": "Create or update payment",
                "parameters": [
                    {
                        "description": "payment",
                        "name": "payment",
                        "in": "body",
                        "required": true,
                        "schema": {
                            "$ref": "#/definitions/domain.Payment"
                        }
                    }
                ],
                "responses": {
                    "200": {
                        "description": "OK",
                        "schema": {
                            "$ref": "#/definitions/domain.Payment"
                        }
                    }
                }
            }
        },
        "/api/payments/{orderId}": {
            "delete": {
                "tags": [
                    "payments"
                ],
                "summary": "Delete payment by order id",
                "parameters": [
                    {
                        "type": "integer",
                        "description": "order id",
                        "name": "orderId",
                        "in": "path",
                        "required": true
                    }
                ],
                "responses": {
                    "204": {
                        "description": "No Content"
                    }
                }
            }
        },
        "/api/products": {
            "get": {
                "produces": [
                    "application/json"
                ],
                "tags": [
                    "products"
                ],
                "summary": "List products",
                "parameters": [
                    {
                        "type": "integer",
                        "description": "limit",
                        "name": "limit",
                        "in": "query"
                    }
                ],
                "responses": {
                    "200": {
                        "description": "OK",
                        "schema": {
                            "type": "array",
                            "items": {
                                "$ref": "#/definitions/domain.Product"
                            }
                        }
                    }
                }
            },
            "post": {
                "consumes": [
                    "application/json"
                ],
                "produces": [
                    "application/json"
                ],
                "tags": [
                    "products"
                ],
                "summary": "Create or update product",
                "parameters": [
                    {
                        "description": "product",
                        "name": "product",
                        "in": "body",
                        "required": true,
                        "schema": {
                            "$ref": "#/definitions/domain.Product"
                        }
                    }
                ],
                "responses": {
                    "200": {
                        "description": "OK",
                        "schema": {
                            "$ref": "#/definitions/domain.Product"
                        }
                    }
                }
            }
        },
        "/api/products/{id}": {
            "delete": {
                "tags": [
                    "products"
                ],
                "summary": "Delete product",
                "parameters": [
                    {
                        "type": "integer",
                        "description": "product id",
                        "name": "id",
                        "in": "path",
                        "required": true
                    }
                ],
                "responses": {
                    "204": {
                        "description": "No Content"
                    }
                }
            }
        },
        "/api/reports/dishes-availability": {
            "get": {
                "produces": [
                    "application/json"
                ],
                "tags": [
                    "reports"
                ],
                "summary": "Dishes availability",
                "responses": {
                    "200": {
                        "description": "OK",
                        "schema": {
                            "type": "array",
                            "items": {
                                "$ref": "#/definitions/domain.DishAvailability"
                            }
                        }
                    }
                }
            }
        },
        "/api/reports/shift-revenue": {
            "get": {
                "produces": [
                    "application/json"
                ],
                "tags": [
                    "reports"
                ],
                "summary": "Shift revenue view",
                "responses": {
                    "200": {
                        "description": "OK",
                        "schema": {
                            "type": "array",
                            "items": {
                                "$ref": "#/definitions/domain.ShiftRevenue"
                            }
                        }
                    }
                }
            }
        },
        "/api/reports/waiters": {
            "get": {
                "produces": [
                    "application/json"
                ],
                "tags": [
                    "reports"
                ],
                "summary": "Waiter performance",
                "responses": {
                    "200": {
                        "description": "OK",
                        "schema": {
                            "type": "array",
                            "items": {
                                "$ref": "#/definitions/domain.WaiterPerformance"
                            }
                        }
                    }
                }
            }
        },
        "/api/reservations": {
            "get": {
                "produces": [
                    "application/json"
                ],
                "tags": [
                    "reservations"
                ],
                "summary": "List reservations",
                "parameters": [
                    {
                        "type": "string",
                        "description": "status filter",
                        "name": "status",
                        "in": "query"
                    }
                ],
                "responses": {
                    "200": {
                        "description": "OK",
                        "schema": {
                            "type": "array",
                            "items": {
                                "$ref": "#/definitions/domain.Reservation"
                            }
                        }
                    }
                }
            },
            "post": {
                "consumes": [
                    "application/json"
                ],
                "produces": [
                    "application/json"
                ],
                "tags": [
                    "reservations"
                ],
                "summary": "Create reservation",
                "parameters": [
                    {
                        "description": "reservation",
                        "name": "reservation",
                        "in": "body",
                        "required": true,
                        "schema": {
                            "$ref": "#/definitions/domain.Reservation"
                        }
                    }
                ],
                "responses": {
                    "201": {
                        "description": "Created",
                        "schema": {
                            "$ref": "#/definitions/domain.Reservation"
                        }
                    }
                }
            }
        },
        "/api/reservations/{id}": {
            "delete": {
                "tags": [
                    "reservations"
                ],
                "summary": "Delete reservation",
                "parameters": [
                    {
                        "type": "integer",
                        "description": "reservation id",
                        "name": "id",
                        "in": "path",
                        "required": true
                    }
                ],
                "responses": {
                    "204": {
                        "description": "No Content"
                    }
                }
            }
        },
        "/api/reservations/{id}/status": {
            "put": {
                "tags": [
                    "reservations"
                ],
                "summary": "Update reservation status",
                "parameters": [
                    {
                        "type": "integer",
                        "description": "reservation id",
                        "name": "id",
                        "in": "path",
                        "required": true
                    },
                    {
                        "type": "string",
                        "description": "new status",
                        "name": "status",
                        "in": "query",
                        "required": true
                    }
                ],
                "responses": {
                    "200": {
                        "description": "OK"
                    }
                }
            }
        },
        "/api/tables": {
            "get": {
                "produces": [
                    "application/json"
                ],
                "tags": [
                    "tables"
                ],
                "summary": "List restaurant tables",
                "responses": {
                    "200": {
                        "description": "OK",
                        "schema": {
                            "type": "array",
                            "items": {
                                "$ref": "#/definitions/domain.RestaurantTable"
                            }
                        }
                    }
                }
            },
            "post": {
                "consumes": [
                    "application/json"
                ],
                "produces": [
                    "application/json"
                ],
                "tags": [
                    "tables"
                ],
                "summary": "Create or update restaurant table",
                "parameters": [
                    {
                        "description": "table",
                        "name": "table",
                        "in": "body",
                        "required": true,
                        "schema": {
                            "$ref": "#/definitions/domain.RestaurantTable"
                        }
                    }
                ],
                "responses": {
                    "200": {
                        "description": "OK",
                        "schema": {
                            "$ref": "#/definitions/domain.RestaurantTable"
                        }
                    }
                }
            }
        },
        "/api/tables/{id}": {
            "delete": {
                "tags": [
                    "tables"
                ],
                "summary": "Delete restaurant table",
                "parameters": [
                    {
                        "type": "integer",
                        "description": "table id",
                        "name": "id",
                        "in": "path",
                        "required": true
                    }
                ],
                "responses": {
                    "204": {
                        "description": "No Content"
                    }
                }
            }
        }
    },
    "definitions": {
        "domain.Customer": {
            "type": "object",
            "properties": {
                "created_at": {
                    "type": "string"
                },
                "email": {
                    "type": "string"
                },
                "full_name": {
                    "type": "string"
                },
                "id": {
                    "type": "integer"
                },
                "phone": {
                    "type": "string"
                },
                "vip_level": {
                    "type": "integer"
                }
            }
        },
        "domain.Dish": {
            "type": "object",
            "properties": {
                "category_id": {
                    "type": "integer"
                },
                "cook_time_minutes": {
                    "type": "integer"
                },
                "description": {
                    "type": "string"
                },
                "id": {
                    "type": "integer"
                },
                "is_active": {
                    "type": "boolean"
                },
                "name": {
                    "type": "string"
                },
                "price": {
                    "type": "number"
                }
            }
        },
        "domain.DishAvailability": {
            "type": "object",
            "properties": {
                "all_products_available": {
                    "type": "boolean"
                },
                "can_be_ordered": {
                    "type": "boolean"
                },
                "id": {
                    "type": "integer"
                },
                "is_active": {
                    "type": "boolean"
                },
                "name": {
                    "type": "string"
                },
                "price": {
                    "type": "number"
                }
            }
        },
        "domain.Employee": {
            "type": "object",
            "properties": {
                "email": {
                    "type": "string"
                },
                "full_name": {
                    "type": "string"
                },
                "hired_at": {
                    "type": "string"
                },
                "id": {
                    "type": "integer"
                },
                "is_active": {
                    "type": "boolean"
                },
                "phone": {
                    "type": "string"
                },
                "role_id": {
                    "type": "integer"
                }
            }
        },
        "domain.MenuCategory": {
            "type": "object",
            "properties": {
                "description": {
                    "type": "string"
                },
                "id": {
                    "type": "integer"
                },
                "is_active": {
                    "type": "boolean"
                },
                "name": {
                    "type": "string"
                },
                "sort_order": {
                    "type": "integer"
                }
            }
        },
        "domain.Order": {
            "type": "object",
            "properties": {
                "created_at": {
                    "type": "string"
                },
                "customer_id": {
                    "type": "integer"
                },
                "id": {
                    "type": "integer"
                },
                "reservation_id": {
                    "type": "integer"
                },
                "shift_id": {
                    "type": "integer"
                },
                "status": {
                    "type": "string"
                },
                "table_id": {
                    "type": "integer"
                },
                "waiter_id": {
                    "type": "integer"
                }
            }
        },
        "domain.OrderItem": {
            "type": "object",
            "properties": {
                "comment": {
                    "type": "string"
                },
                "dish_id": {
                    "type": "integer"
                },
                "id": {
                    "type": "integer"
                },
                "order_id": {
                    "type": "integer"
                },
                "price_at_moment": {
                    "type": "number"
                },
                "quantity": {
                    "type": "integer"
                }
            }
        },
        "domain.Payment": {
            "type": "object",
            "properties": {
                "amount": {
                    "type": "number"
                },
                "id": {
                    "type": "integer"
                },
                "method": {
                    "type": "string"
                },
                "order_id": {
                    "type": "integer"
                },
                "paid_at": {
                    "type": "string"
                },
                "status": {
                    "type": "string"
                }
            }
        },
        "domain.Product": {
            "type": "object",
            "properties": {
                "cost_price": {
                    "type": "number"
                },
                "id": {
                    "type": "integer"
                },
                "is_available": {
                    "type": "boolean"
                },
                "name": {
                    "type": "string"
                },
                "unit": {
                    "type": "string"
                }
            }
        },
        "domain.Reservation": {
            "type": "object",
            "properties": {
                "created_at": {
                    "type": "string"
                },
                "customer_id": {
                    "type": "integer"
                },
                "id": {
                    "type": "integer"
                },
                "reserved_from": {
                    "type": "string"
                },
                "reserved_to": {
                    "type": "string"
                },
                "status": {
                    "type": "string"
                },
                "table_id": {
                    "type": "integer"
                }
            }
        },
        "domain.RestaurantTable": {
            "type": "object",
            "properties": {
                "description": {
                    "type": "string"
                },
                "id": {
                    "type": "integer"
                },
                "is_active": {
                    "type": "boolean"
                },
                "seats": {
                    "type": "integer"
                },
                "table_number": {
                    "type": "integer"
                }
            }
        },
        "domain.ShiftRevenue": {
            "type": "object",
            "properties": {
                "avg_check": {
                    "type": "number"
                },
                "closed_at": {
                    "type": "string"
                },
                "opened_at": {
                    "type": "string"
                },
                "orders_count": {
                    "type": "integer"
                },
                "shift_id": {
                    "type": "integer"
                },
                "total_revenue": {
                    "type": "number"
                }
            }
        },
        "domain.WaiterPerformance": {
            "type": "object",
            "properties": {
                "avg_check": {
                    "type": "number"
                },
                "full_name": {
                    "type": "string"
                },
                "orders_count": {
                    "type": "integer"
                },
                "total_revenue": {
                    "type": "number"
                },
                "waiter_id": {
                    "type": "integer"
                }
            }
        },
        "handlers.orderRequest": {
            "type": "object",
            "properties": {
                "customer_id": {
                    "type": "integer"
                },
                "items": {
                    "type": "array",
                    "items": {
                        "$ref": "#/definitions/domain.OrderItem"
                    }
                },
                "reservation_id": {
                    "type": "integer"
                },
                "shift_id": {
                    "type": "integer"
                },
                "status": {
                    "type": "string"
                },
                "table_id": {
                    "type": "integer"
                },
                "waiter_id": {
                    "type": "integer"
                }
            }
        }
    }
}